{"status":"0","msg":"ok","result":{"barcode":"6902265240501","name":"海天老抽王500ml*12瓶非转基因黄豆酿造 烹饪调味品居家","ename":"","unspsc":"","brand":"海天","type":"","width":"","height":"","depth":"","origincountry":"佛山市海天(高明)调味食品有限","originplace":"广东","assemblycountry":"","barcodetype":"","catena":"","isbasicunit":"0","packagetype":"","grossweight":"","netcontent":"500ml*12瓶\/箱","netweight":"500（ml）","description":"","keyword":"","pic":"http:\/\/api.jisuapi.com\/barcode2\/upload\/20170208\/123818_53228.jpg","price":"","licensenum":"","healthpermitnum":"","company":""}}