{"status":"0","msg":"ok","result":{"brand":"山城味美食","originplace":"重庆","barcode":"6923807807129","netcontent":"瓶装,野香菌,竹笋,木耳,大头菜,什锦","description":"阴凉通风干燥处","unspsc":"","type":"","width":"","height":"","depth":"","origincountry":"","assemblycountry":"","barcodetype":"","catena":"","isbasicunit":"","packagetype":"","grossweight":"","netweight":"","keyword":"","price":"","licensenum":"","healthpermitnum":"","name":"四川特产饭扫光菌笋蕨菜280g下饭菜酱菜拌面拌饭酱咸菜泡菜酸","pic":"http:\/\/api.jisuapi.com\/barcode2\/upload\/20170410\/145118_36344.jpg"}}