{"status":"0","msg":"ok","result":{"barcode":"6928497820038","name":"四川特产 批发休闲零食 品品人生逗嘴泡椒凤爪 168g一件代","ename":"","unspsc":"","brand":"品品","type":"","width":"","height":"","depth":"","origincountry":"成都品品人生食品有限公司","originplace":"四川","assemblycountry":"","barcodetype":"","catena":"","isbasicunit":"0","packagetype":"","grossweight":"","netcontent":"25*168g","netweight":"","description":"常温,避光,防潮,勿压","keyword":"","pic":"http:\/\/api.jisuapi.com\/barcode2\/upload\/20161026\/150030_97289.jpg","price":"￥310.00","licensenum":"510004018321","healthpermitnum":"","company":""}}